rivery_cli/__init__.py
rivery_cli/client.py
rivery_cli/main.py
rivery_cli/rivery_session.py
rivery_cli/cli/__init__.py
rivery_cli/cli/activities.py
rivery_cli/cli/base.py
rivery_cli/cli/configure.py
rivery_cli/cli/init.py
rivery_cli/cli/profiles.py
rivery_cli/cli/rivers.py
rivery_cli/converters/__init__.py
rivery_cli/converters/yaml_converters.py
rivery_cli/converters/entities/__init__.py
rivery_cli/converters/entities/rivers.py
rivery_cli/globals/__init__.py
rivery_cli/globals/global_keys.py
rivery_cli/globals/global_settings.py
rivery_cli/utils/__init__.py
rivery_cli/utils/bson_utils.py
rivery_cli/utils/decorators.py
rivery_cli/utils/logicode_utils.py
rivery_cli/utils/path_utils.py
rivery_cli/utils/utils.py
rivery_cli/utils/yaml_loaders.py
tests/__init__.py
tests/test_cli_activities.py
tests/test_cli_profiles.py
tests/test_cli_rivers.py
tests/test_init.py
tests/test_path_utils.py
rivery_cli-0.4.0.dist-info/METADATA
rivery_cli-0.4.0.dist-info/WHEEL
rivery_cli-0.4.0.dist-info/entry_points.txt
rivery_cli-0.4.0.dist-info/top_level.txt
rivery_cli-0.4.0.dist-info/RECORD
