Metadata-Version: 2.1
Name: rivery-cli
Version: 0.4.0
Summary: UNKNOWN
Home-page: UNKNOWN
Author: Rivery
License: UNKNOWN
Platform: UNKNOWN
Requires-Dist: click (>=7.1.2)
Requires-Dist: jsonschema (>=3.2.0)
Requires-Dist: jsonschema-extended (>=0.6)
Requires-Dist: requests (>=2.25.1)
Requires-Dist: simplejson (>=3.17.2)
Requires-Dist: yaql (>=1.0.0)
Requires-Dist: colorama (>=0.4.3)
Requires-Dist: six (>=1.15.0)
Requires-Dist: urllib3 (>=1.26.3)
Requires-Dist: PyYAML (>=5.4.1)
Requires-Dist: attrs (>=20.3.0)
Requires-Dist: bson (>=0.5.10)
Requires-Dist: click-spinner (==0.1.10)
Requires-Dist: setuptools (~=57.0.0)
Requires-Dist: prettytable (~=2.1.0)
